Workbook

Sheet Assumptions
A1: Agrawal Family Financial Scenario Planning
A3: Key Assumptions
A5: Initial Capital ($) | B5: 1700000
A6: Initial Cost Basis ($) | B6: 500000
A7: Initial Cost Basis Ratio (%) | B7: =B6/B5 -> 0.29411765
A9: After-Tax Take-Home Needed ($) | B9: 240000
A11: Investment Return (%) | B11: 0.09
A12: Line of Credit Interest Rate (%) | B12: 0.05
A13: LOC to Equity Ratio (%) | B13: 0.7
A15: Starting Age | B15: 40
A16: Ending Age | B16: 100
A18: Planning Horizon (Years) | B18: =B16-B15 -> 60
A20: Tax Rates (Married Filing Jointly)
A21: Federal LTCG Tax Rate (%) | B21: 0.16
A22: Federal NIIT Tax Rate (%) | B22: 0.038
A23: CA Marginal Tax Rate (%) | B23: 0.07
A24: Combined Tax Rate on Gains (%) | B24: =B21+B22+B23 -> 0.268
A26: Note: LOC interest is NOT tax deductible

Sheet Scenario 1 - After-Tax $500K
A1: Scenario 1: Withdraw Enough to Net $500K After-Tax
A4: Year | B4: Age | C4: Beginning Balance ($) | D4: Cost Basis ($) | E4: Cost Basis Ratio (%) | F4: Gross Withdrawal ($) | G4: Return of Basis ($) | H4: Capital Gain ($) | I4: Tax on Gain ($) | J4: After-Tax Take-Home ($) | K4: Investment Return ($) | L4: Ending Balance ($)
A5: 1 | B5: 40 | C5: =Assumptions!$B$5 -> 1700000 | D5: =Assumptions!$B$6 -> 500000 | E5: =D5/C5 -> 0.29411765 | F5: =Assumptions!$B$9/(1-(1-E5)*Assumptions!$B$24) -> 295995.36 | G5: =F5*E5 -> 87057.458 | H5: =F5-G5 -> 208937.9 | I5: =H5*Assumptions!$B$24 -> 55995.357 | J5: =F5-I5 -> 240000 | K5: =C5*Assumptions!$B$11 -> 153000 | L5: =C5+K5-F5 -> 1557004.6
A6: 2 | B6: 41 | C6: =L5 -> 1557004.6 | D6: =D5-G5 -> 412942.54 | E6: =D6/C6 -> 0.265216 | F6: =Assumptions!$B$9/(1-(1-E6)*Assumptions!$B$24) -> 298850.22 | G6: =F6*E6 -> 79259.859 | H6: =F6-G6 -> 219590.36 | I6: =H6*Assumptions!$B$24 -> 58850.216 | J6: =F6-I6 -> 240000 | K6: =C6*Assumptions!$B$11 -> 140130.42 | L6: =C6+K6-F6 -> 1398284.8
A7: 3 | B7: 42 | C7: =L6 -> 1398284.8 | D7: =D6-G6 -> 333682.68 | E7: =D7/C7 -> 0.23863713 | F7: =Assumptions!$B$9/(1-(1-E7)*Assumptions!$B$24) -> 301524.68 | G7: =F7*E7 -> 71954.984 | H7: =F7-G7 -> 229569.69 | I7: =H7*Assumptions!$B$24 -> 61524.678 | J7: =F7-I7 -> 240000 | K7: =C7*Assumptions!$B$11 -> 125845.64 | L7: =C7+K7-F7 -> 1222605.8
A8: 4 | B8: 43 | C8: =L7 -> 1222605.8 | D8: =D7-G7 -> 261727.7 | E8: =D8/C8 -> 0.21407366 | F8: =Assumptions!$B$9/(1-(1-E8)*Assumptions!$B$24) -> 304039.26 | G8: =F8*E8 -> 65086.797 | H8: =F8-G8 -> 238952.46 | I8: =H8*Assumptions!$B$24 -> 64039.26 | J8: =F8-I8 -> 240000 | K8: =C8*Assumptions!$B$11 -> 110034.52 | L8: =C8+K8-F8 -> 1028601.1
A9: 5 | B9: 44 | C9: =L8 -> 1028601.1 | D9: =D8-G8 -> 196640.9 | E9: =D9/C9 -> 0.19117315 | F9: =Assumptions!$B$9/(1-(1-E9)*Assumptions!$B$24) -> 306421.68 | G9: =F9*E9 -> 58579.596 | H9: =F9-G9 -> 247842.08 | I9: =H9*Assumptions!$B$24 -> 66421.678 | J9: =F9-I9 -> 240000 | K9: =C9*Assumptions!$B$11 -> 92574.096 | L9: =C9+K9-F9 -> 814753.48
A10: 6 | B10: 45 | C10: =L9 -> 814753.48 | D10: =D9-G9 -> 138061.31 | E10: =D10/C10 -> 0.16945163 | F10: =Assumptions!$B$9/(1-(1-E10)*Assumptions!$B$24) -> 308716.2 | G10: =F10*E10 -> 52312.464 | H10: =F10-G10 -> 256403.74 | I10: =H10*Assumptions!$B$24 -> 68716.202 | J10: =F10-I10 -> 240000 | K10: =C10*Assumptions!$B$11 -> 73327.814 | L10: =C10+K10-F10 -> 579365.1
A11: 7 | B11: 46 | C11: =L10 -> 579365.1 | D11: =D10-G10 -> 85748.842 | E11: =D11/C11 -> 0.14800485 | F11: =Assumptions!$B$9/(1-(1-E11)*Assumptions!$B$24) -> 311015.67 | G11: =F11*E11 -> 46031.827 | H11: =F11-G11 -> 264983.84 | I11: =H11*Assumptions!$B$24 -> 71015.67 | J11: =F11-I11 -> 240000 | K11: =C11*Assumptions!$B$11 -> 52142.859 | L11: =C11+K11-F11 -> 320492.28
A12: 8 | B12: 47 | C12: =L11 -> 320492.28 | D12: =D11-G11 -> 39717.016 | E12: =D12/C12 -> 0.12392503 | F12: =Assumptions!$B$9/(1-(1-E12)*Assumptions!$B$24) -> 313638.61 | G12: =F12*E12 -> 38867.674 | H12: =F12-G12 -> 274770.94 | I12: =H12*Assumptions!$B$24 -> 73638.611 | J12: =F12-I12 -> 240000 | K12: =C12*Assumptions!$B$11 -> 28844.306 | L12: =C12+K12-F12 -> 35697.978
A13: 9 | B13: 48 | C13: =L12 -> 35697.978 | D13: =D12-G12 -> 849.34159 | E13: =D13/C13 -> 0.023792428 | F13: =Assumptions!$B$9/(1-(1-E13)*Assumptions!$B$24) -> 325037.49 | G13: =F13*E13 -> 7733.4312 | H13: =F13-G13 -> 317304.06 | I13: =H13*Assumptions!$B$24 -> 85037.487 | J13: =F13-I13 -> 240000 | K13: =C13*Assumptions!$B$11 -> 3212.818 | L13: =C13+K13-F13 -> -286126.69
A14: 10 | B14: 49 | C14: =L13 -> -286126.69 | D14: =D13-G13 -> -6884.0896 | E14: =D14/C14 -> 0.024059585 | F14: =Assumptions!$B$9/(1-(1-E14)*Assumptions!$B$24) -> 325005.97 | G14: =F14*E14 -> 7819.509 | H14: =F14-G14 -> 317186.46 | I14: =H14*Assumptions!$B$24 -> 85005.972 | J14: =F14-I14 -> 240000 | K14: =C14*Assumptions!$B$11 -> -25751.402 | L14: =C14+K14-F14 -> -636884.06
A15: 11 | B15: 50 | C15: =L14 -> -636884.06 | D15: =D14-G14 -> -14703.599 | E15: =D15/C15 -> 0.023086774 | F15: =Assumptions!$B$9/(1-(1-E15)*Assumptions!$B$24) -> 325120.76 | G15: =F15*E15 -> 7505.9895 | H15: =F15-G15 -> 317614.77 | I15: =H15*Assumptions!$B$24 -> 85120.758 | J15: =F15-I15 -> 240000 | K15: =C15*Assumptions!$B$11 -> -57319.566 | L15: =C15+K15-F15 -> -1019324.4
A16: 12 | B16: 51 | C16: =L15 -> -1019324.4 | D16: =D15-G15 -> -22209.588 | E16: =D16/C16 -> 0.021788538 | F16: =Assumptions!$B$9/(1-(1-E16)*Assumptions!$B$24) -> 325274.07 | G16: =F16*E16 -> 7087.2463 | H16: =F16-G16 -> 318186.82 | I16: =H16*Assumptions!$B$24 -> 85274.068 | J16: =F16-I16 -> 240000 | K16: =C16*Assumptions!$B$11 -> -91739.195 | L16: =C16+K16-F16 -> -1436337.7
A17: 13 | B17: 52 | C17: =L16 -> -1436337.7 | D17: =D16-G16 -> -29296.834 | E17: =D17/C17 -> 0.020396899 | F17: =Assumptions!$B$9/(1-(1-E17)*Assumptions!$B$24) -> 325438.57 | G17: =F17*E17 -> 6637.9377 | H17: =F17-G17 -> 318800.63 | I17: =H17*Assumptions!$B$24 -> 85438.569 | J17: =F17-I17 -> 240000 | K17: =C17*Assumptions!$B$11 -> -129270.39 | L17: =C17+K17-F17 -> -1891046.6
... A65: 61 | B65: 100 | C65: =L64 -> -313325634 | D65: =D64-G64 -> -113683.28 | E65: =D65/C65 -> 0.0003628279 | F65: =Assumptions!$B$9/(1-(1-E65)*Assumptions!$B$24) -> 327825.3 | G65: =F65*E65 -> 118.94417 | H65: =F65-G65 -> 327706.36 | I65: =H65*Assumptions!$B$24 -> 87825.305 | J65: =F65-I65 -> 240000 | K65: =C65*Assumptions!$B$11 -> -28199307 | L65: =C65+K65-F65 -> -3.4185277e+08

Sheet Scenario 2 - LOC $500K
A1: Scenario 2: Borrow $500K/year from LOC
A4: Year | B4: Age | C4: Beginning Equity ($) | D4: Investment Return ($) | E4: Ending Equity ($) | F4: Expenses Drawn ($) | G4: LOC Balance ($) | H4: LOC Interest ($) | I4: Available LOC ($) | J4: LOC Capacity ($)
A5: 1 | B5: 40 | C5: =Assumptions!$B$5 -> 1700000 | D5: =C5*Assumptions!$B$11 -> 153000 | E5: =C5+D5 -> 1853000 | F5: =Assumptions!$B$9 -> 240000 | G5: =F5 -> 240000 | H5: =G5*Assumptions!$B$12 -> 12000 | I5: =E5*Assumptions!$B$13 -> 1297100 | J5: =I5-G5 -> 1057100
A6: 2 | B6: 41 | C6: =E5 -> 1853000 | D6: =C6*Assumptions!$B$11 -> 166770 | E6: =C6+D6 -> 2019770 | F6: =Assumptions!$B$9 -> 240000 | G6: =G5+F6+H5 -> 492000 | H6: =G6*Assumptions!$B$12 -> 24600 | I6: =E6*Assumptions!$B$13 -> 1413839 | J6: =I6-G6 -> 921839
A7: 3 | B7: 42 | C7: =E6 -> 2019770 | D7: =C7*Assumptions!$B$11 -> 181779.3 | E7: =C7+D7 -> 2201549.3 | F7: =Assumptions!$B$9 -> 240000 | G7: =G6+F7+H6 -> 756600 | H7: =G7*Assumptions!$B$12 -> 37830 | I7: =E7*Assumptions!$B$13 -> 1541084.5 | J7: =I7-G7 -> 784484.51
A8: 4 | B8: 43 | C8: =E7 -> 2201549.3 | D8: =C8*Assumptions!$B$11 -> 198139.44 | E8: =C8+D8 -> 2399688.7 | F8: =Assumptions!$B$9 -> 240000 | G8: =G7+F8+H7 -> 1034430 | H8: =G8*Assumptions!$B$12 -> 51721.5 | I8: =E8*Assumptions!$B$13 -> 1679782.1 | J8: =I8-G8 -> 645352.12
A9: 5 | B9: 44 | C9: =E8 -> 2399688.7 | D9: =C9*Assumptions!$B$11 -> 215971.99 | E9: =C9+D9 -> 2615660.7 | F9: =Assumptions!$B$9 -> 240000 | G9: =G8+F9+H8 -> 1326151.5 | H9: =G9*Assumptions!$B$12 -> 66307.575 | I9: =E9*Assumptions!$B$13 -> 1830962.5 | J9: =I9-G9 -> 504811.01
A10: 6 | B10: 45 | C10: =E9 -> 2615660.7 | D10: =C10*Assumptions!$B$11 -> 235409.47 | E10: =C10+D10 -> 2851070.2 | F10: =Assumptions!$B$9 -> 240000 | G10: =G9+F10+H9 -> 1632459.1 | H10: =G10*Assumptions!$B$12 -> 81622.954 | I10: =E10*Assumptions!$B$13 -> 1995749.1 | J10: =I10-G10 -> 363290.06 | L10: =E10-G10-(G10*0.75*20%) -> 973742.25
A11: 7 | B11: 46 | C11: =E10 -> 2851070.2 | D11: =C11*Assumptions!$B$11 -> 256596.32 | E11: =C11+D11 -> 3107666.5 | F11: =Assumptions!$B$9 -> 240000 | G11: =G10+F11+H10 -> 1954082 | H11: =G11*Assumptions!$B$12 -> 97704.101 | I11: =E11*Assumptions!$B$13 -> 2175366.6 | J11: =I11-G11 -> 221284.52
A12: 8 | B12: 47 | C12: =E11 -> 3107666.5 | D12: =C12*Assumptions!$B$11 -> 279689.99 | E12: =C12+D12 -> 3387356.5 | F12: =Assumptions!$B$9 -> 240000 | G12: =G11+F12+H11 -> 2291786.1 | H12: =G12*Assumptions!$B$12 -> 114589.31 | I12: =E12*Assumptions!$B$13 -> 2371149.5 | J12: =I12-G12 -> 79363.413
A13: 9 | B13: 48 | C13: =E12 -> 3387356.5 | D13: =C13*Assumptions!$B$11 -> 304862.08 | E13: =C13+D13 -> 3692218.6 | F13: =Assumptions!$B$9 -> 240000 | G13: =G12+F13+H12 -> 2646375.4 | H13: =G13*Assumptions!$B$12 -> 132318.77 | I13: =E13*Assumptions!$B$13 -> 2584553 | J13: =I13-G13 -> -61822.434
A14: 10 | B14: 49 | C14: =E13 -> 3692218.6 | D14: =C14*Assumptions!$B$11 -> 332299.67 | E14: =C14+D14 -> 4024518.2 | F14: =Assumptions!$B$9 -> 240000 | G14: =G13+F14+H13 -> 3018694.2 | H14: =G14*Assumptions!$B$12 -> 150934.71 | I14: =E14*Assumptions!$B$13 -> 2817162.8 | J14: =I14-G14 -> -201531.44
A15: 11 | B15: 50 | C15: =E14 -> 4024518.2 | D15: =C15*Assumptions!$B$11 -> 362206.64 | E15: =C15+D15 -> 4386724.9 | F15: =Assumptions!$B$9 -> 240000 | G15: =G14+F15+H14 -> 3409628.9 | H15: =G15*Assumptions!$B$12 -> 170481.45 | I15: =E15*Assumptions!$B$13 -> 3070707.4 | J15: =I15-G15 -> -338921.5
A16: 12 | B16: 51 | C16: =E15 -> 4386724.9 | D16: =C16*Assumptions!$B$11 -> 394805.24 | E16: =C16+D16 -> 4781530.1 | F16: =Assumptions!$B$9 -> 240000 | G16: =G15+F16+H15 -> 3820110.4 | H16: =G16*Assumptions!$B$12 -> 191005.52 | I16: =E16*Assumptions!$B$13 -> 3347071.1 | J16: =I16-G16 -> -473039.27
A17: 13 | B17: 52 | C17: =E16 -> 4781530.1 | D17: =C17*Assumptions!$B$11 -> 430337.71 | E17: =C17+D17 -> 5211867.8 | F17: =Assumptions!$B$9 -> 240000 | G17: =G16+F17+H16 -> 4251115.9 | H17: =G17*Assumptions!$B$12 -> 212555.79 | I17: =E17*Assumptions!$B$13 -> 3648307.5 | J17: =I17-G17 -> -602808.39
A18: 14 | B18: 53 | C18: =E17 -> 5211867.8 | D18: =C18*Assumptions!$B$11 -> 469068.11 | E18: =C18+D18 -> 5680935.9 | F18: =Assumptions!$B$9 -> 240000 | G18: =G17+F18+H17 -> 4703671.7 | H18: =G18*Assumptions!$B$12 -> 235183.58 | I18: =E18*Assumptions!$B$13 -> 3976655.2 | J18: =I18-G18 -> -727016.51
A19: 15 | B19: 54 | C19: =E18 -> 5680935.9 | D19: =C19*Assumptions!$B$11 -> 511284.24 | E19: =C19+D19 -> 6192220.2 | F19: =Assumptions!$B$9 -> 240000 | G19: =G18+F19+H18 -> 5178855.3 | H19: =G19*Assumptions!$B$12 -> 258942.76 | I19: =E19*Assumptions!$B$13 -> 4334554.1 | J19: =I19-G19 -> -844301.13
A20: 16 | B20: 55 | C20: =E19 -> 6192220.2 | D20: =C20*Assumptions!$B$11 -> 557299.82 | E20: =C20+D20 -> 6749520 | F20: =Assumptions!$B$9 -> 240000 | G20: =G19+F20+H19 -> 5677798 | H20: =G20*Assumptions!$B$12 -> 283889.9 | I20: =E20*Assumptions!$B$13 -> 4724664 | J20: =I20-G20 -> -953134.03
A21: 17 | B21: 56 | C21: =E20 -> 6749520 | D21: =C21*Assumptions!$B$11 -> 607456.8 | E21: =C21+D21 -> 7356976.8 | F21: =Assumptions!$B$9 -> 240000 | G21: =G20+F21+H20 -> 6201687.9 | H21: =G21*Assumptions!$B$12 -> 310084.4 | I21: =E21*Assumptions!$B$13 -> 5149883.8 | J21: =I21-G21 -> -1051804.2
A22: 18 | B22: 57 | C22: =E21 -> 7356976.8 | D22: =C22*Assumptions!$B$11 -> 662127.91 | E22: =C22+D22 -> 8019104.7 | F22: =Assumptions!$B$9 -> 240000 | G22: =G21+F22+H21 -> 6751772.3 | H22: =G22*Assumptions!$B$12 -> 337588.62 | I22: =E22*Assumptions!$B$13 -> 5613373.3 | J22: =I22-G22 -> -1138399
... A65: 61 | B65: 100 | C65: =E64 -> 2.992532e+08 | D65: =C65*Assumptions!$B$11 -> 26932788 | E65: =C65+D65 -> 326185984 | F65: =Assumptions!$B$9 -> 240000 | G65: =G64+F65+H64 -> 89343097 | H65: =G65*Assumptions!$B$12 -> 4467154.8 | I65: =E65*Assumptions!$B$13 -> 2.2833019e+08 | J65: =I65-G65 -> 1.3898709e+08

Sheet 10-Year Milestones
A1: 10-Year Milestones (Both Net $500K After-Tax)
A3: Age | B3: S1: Balance ($) | C3: S1: Gross Withdrawal ($) | D3: S1: Tax ($) | E3: S2: Equity ($) | F3: S2: LOC Balance ($) | G3: S2: LOC Interest ($) | H3: S2: Net Worth ($) | I3: Difference ($)
A4: 40 | B4: ='Scenario 1 - After-Tax $500K'!L5 -> 1557004.6 | C4: ='Scenario 1 - After-Tax $500K'!F5 -> 295995.36 | D4: ='Scenario 1 - After-Tax $500K'!I5 -> 55995.357 | E4: ='Scenario 2 - LOC $500K'!E5 -> 1853000 | F4: ='Scenario 2 - LOC $500K'!G5 -> 240000 | G4: ='Scenario 2 - LOC $500K'!H5 -> 12000 | H4: =E4-F4 -> 1613000 | I4: =H4-B4 -> 55995.357
A5: 50 | B5: ='Scenario 1 - After-Tax $500K'!L15 -> -1019324.4 | C5: ='Scenario 1 - After-Tax $500K'!F15 -> 325120.76 | D5: ='Scenario 1 - After-Tax $500K'!I15 -> 85120.758 | E5: ='Scenario 2 - LOC $500K'!E15 -> 4386724.9 | F5: ='Scenario 2 - LOC $500K'!G15 -> 3409628.9 | G5: ='Scenario 2 - LOC $500K'!H15 -> 170481.45 | H5: =E5-F5 -> 977095.97 | I5: =H5-B5 -> 1996420.4
A6: 60 | B6: ='Scenario 1 - After-Tax $500K'!L25 -> -7363846 | C6: ='Scenario 1 - After-Tax $500K'!F25 -> 326558.01 | D6: ='Scenario 1 - After-Tax $500K'!I25 -> 86558.015 | E6: ='Scenario 2 - LOC $500K'!E25 -> 10384973 | F6: ='Scenario 2 - LOC $500K'!G25 -> 8572620.4 | G6: ='Scenario 2 - LOC $500K'!H25 -> 428631.02 | H6: =E6-F6 -> 1812352.7 | I6: =H6-B6 -> 9176198.7
A7: 70 | B7: ='Scenario 1 - After-Tax $500K'!L35 -> -22400446 | C7: ='Scenario 1 - After-Tax $500K'!F35 -> 327299.89 | D7: ='Scenario 1 - After-Tax $500K'!I35 -> 87299.891 | E7: ='Scenario 2 - LOC $500K'!E35 -> 24585008 | F7: ='Scenario 2 - LOC $500K'!G35 -> 16982590 | G7: ='Scenario 2 - LOC $500K'!H35 -> 849129.48 | H7: =E7-F7 -> 7602418.6 | I7: =H7-B7 -> 30002865
A8: 80 | B8: ='Scenario 1 - After-Tax $500K'!L45 -> -58005380 | C8: ='Scenario 1 - After-Tax $500K'!F45 -> 327626.14 | D8: ='Scenario 1 - After-Tax $500K'!I45 -> 87626.143 | E8: ='Scenario 2 - LOC $500K'!E45 -> 58201655 | F8: ='Scenario 2 - LOC $500K'!G45 -> 30681543 | G8: ='Scenario 2 - LOC $500K'!H45 -> 1534077.2 | H8: =E8-F8 -> 27520112 | I8: =H8-B8 -> 85525492
A9: 90 | B9: ='Scenario 1 - After-Tax $500K'!L55 -> -1.422986e+08 | C9: ='Scenario 1 - After-Tax $500K'!F55 -> 327765.93 | D9: ='Scenario 1 - After-Tax $500K'!I55 -> 87765.926 | E9: ='Scenario 2 - LOC $500K'!E55 -> 1.3778448e+08 | F9: ='Scenario 2 - LOC $500K'!G55 -> 52995695 | G9: ='Scenario 2 - LOC $500K'!H55 -> 2649784.7 | H9: =E9-F9 -> 84788790 | I9: =H9-B9 -> 2.2708739e+08
A10: 100 | B10: ='Scenario 1 - After-Tax $500K'!L65 -> -3.4185277e+08 | C10: ='Scenario 1 - After-Tax $500K'!F65 -> 327825.3 | D10: ='Scenario 1 - After-Tax $500K'!I65 -> 87825.305 | E10: ='Scenario 2 - LOC $500K'!E65 -> 326185984 | F10: ='Scenario 2 - LOC $500K'!G65 -> 89343097 | G10: ='Scenario 2 - LOC $500K'!H65 -> 4467154.8 | H10: =E10-F10 -> 2.3684289e+08 | I10: =H10-B10 -> 5.7869565e+08

Sheet Sell Options
A1: Neel's Portfolio
A2: Equity | B2: Per week avg bid price at 90% chance of profit | C2: Per contract per week | D2: Portfolio | E2: Total Weekly Earnings | F2: Unit Price in Nov | G2: Capital at play | H2: Weekly %age Return | I2: Annual %age Return
A3: VOO | B3: 0.31 | C3: =B3*100 -> 31 | D3: 0 | E3: =C3*D3 -> 0 | F3: 616 | G3: =D3*F3*100 -> 0 | H3: =E3/G3 -> #DIV/0! | I3: =H3*52 -> #DIV/0!
A4: NETFLIX | B4: 2.78 | C4: =B4*100 -> 278 | D4: 0 | E4: =C4*D4 -> 0 | F4: 1100 | G4: =D4*F4*100 -> 0 | H4: =E4/G4 -> #DIV/0! | I4: =H4*52 -> #DIV/0!
A5: HOOD | B5: 0.82 | C5: =B5*100 -> 82 | D5: 2 | E5: =C5*D5 -> 164 | F5: 127 | G5: =D5*F5*100 -> 25400 | H5: =E5/G5 -> 0.0064566929 | I5: =H5*52 -> 0.33574803
A6: TSLA | B6: 2.5 | C6: =B6*100 -> 250 | D6: 9 | E6: =C6*D6 -> 2250 | F6: 448 | G6: =D6*F6*100 -> 403200 | H6: =E6/G6 -> 0.0055803571 | I6: =H6*52 -> 0.29017857
A7: PLTR | B7: 0.96 | C7: =B7*100 -> 96 | D7: 2 | E7: =C7*D7 -> 192 | F7: 175 | G7: =D7*F7*100 -> 35000 | H7: =E7/G7 -> 0.0054857143 | I7: =H7*52 -> 0.28525714
A8: BABA | B8: 0.72 | C8: =B8*100 -> 72 | D8: 1 | E8: =C8*D8 -> 72 | F8: 165 | G8: =D8*F8*100 -> 16500 | H8: =E8/G8 -> 0.0043636364 | I8: =H8*52 -> 0.22690909
A9: NVDA | B9: 0.71 | C9: =B9*100 -> 71 | D9: 2 | E9: =C9*D9 -> 142 | F9: 187 | G9: =D9*F9*100 -> 37400 | H9: =E9/G9 -> 0.0037967914 | I9: =H9*52 -> 0.19743316
A10: IBIT | B10: 0.21 | C10: =B10*100 -> 21 | D10: 15 | E10: =C10*D10 -> 315 | F10: 58 | G10: =D10*F10*100 -> 87000 | H10: =E10/G10 -> 0.0036206897 | I10: =H10*52 -> 0.18827586
A11: AVGO | B11: 1.23 | C11: =B11*100 -> 123 | D11: 2 | E11: =C11*D11 -> 246 | F11: 353 | G11: =D11*F11*100 -> 70600 | H11: =E11/G11 -> 0.0034844193 | I11: =H11*52 -> 0.1811898
A12: META | B12: 1.9 | C12: =B12*100 -> 190 | D12: 0.4 | E12: =C12*D12 -> 76 | F12: 618 | G12: =D12*F12*100 -> 24720 | H12: =E12/G12 -> 0.0030744337 | I12: =H12*52 -> 0.15987055
A13: MSFT | B13: 0.95 | C13: =B13*100 -> 95 | D13: 0.45 | E13: =C13*D13 -> 42.75 | F13: 495 | G13: =D13*F13*100 -> 22275 | H13: =E13/G13 -> 0.0019191919 | I13: =H13*52 -> 0.09979798
A14: AAPLE | B14: 0.43 | C14: =B14*100 -> 43 | D14: 17 | E14: =C14*D14 -> 731 | F14: 270 | G14: =D14*F14*100 -> 459000 | H14: =E14/G14 -> 0.0015925926 | I14: =H14*52 -> 0.082814815
A15: GLD | B15: 0.46 | C15: =B15*100 -> 46 | D15: 1 | E15: =C15*D15 -> 46 | F15: 367 | G15: =D15*F15*100 -> 36700 | H15: =E15/G15 -> 0.001253406 | I15: =H15*52 -> 0.065177112
A16: FIG | D16: 2 | F16: 40 | G16: =D16*F16*100 -> 8000
A17: TOTAL | E17: =SUM(E3:E14) -> 4230.75 | G17: =SUM(G3:G14) -> 1181095 | H17: =E17/G17 -> 0.0035820573 | I17: =H17*52 -> 0.18626698
A22: Jaya's Portfolio
A23: Equity | B23: Per week avg bid price at 90% chance of profit | C23: Per contract per week | D23: Portfolio | E23: Total Weekly Earnings | F23: Unit Price in Nov | G23: Capital at play | H23: Weekly %age Return | I23: Annual %age Return
A24: TSLA | B24: 2.5 | C24: =B24*100 -> 250 | D24: 6 | E24: =C24*D24 -> 1500 | F24: 448 | G24: =D24*F24*100 -> 268800 | H24: =E24/G24 -> 0.0055803571 | I24: =H24*52 -> 0.29017857
A25: NVDA | B25: 0.71 | C25: =B25*100 -> 71 | D25: 6 | E25: =C25*D25 -> 426 | F25: 187 | G25: =D25*F25*100 -> 112200 | H25: =E25/G25 -> 0.0037967914 | I25: =H25*52 -> 0.19743316
A26: IBIT | B26: 0.21 | C26: =B26*100 -> 21 | D26: 2 | E26: =C26*D26 -> 42 | F26: 58 | G26: =D26*F26*100 -> 11600 | H26: =E26/G26 -> 0.0036206897 | I26: =H26*52 -> 0.18827586
A27: AAPLE | B27: 0.43 | C27: =B27*100 -> 43 | D27: 1 | E27: =C27*D27 -> 43 | F27: 270 | G27: =D27*F27*100 -> 27000 | H27: =E27/G27 -> 0.0015925926 | I27: =H27*52 -> 0.082814815
A28: COIN | B28: 1.96 | C28: =B28*100 -> 196 | D28: 1 | E28: =C28*D28 -> 196 | F28: 300 | G28: =D28*F28*100 -> 30000 | H28: =E28/G28 -> 0.0065333333 | I28: =H28*52 -> 0.33973333
A29: TOTAL | E29: =SUM(E24:E28) -> 2207 | G29: =SUM(G24:G28) -> 449600 | H29: =E29/G29 -> 0.0049088078 | I29: =H29*52 -> 0.25525801
